byte_search/__init__.py
byte_search/cnn.py
byte_search/index.py
byte_search/model.py
byte_search/tokenizer.py
byte_search-0.5.9.dist-info/LICENSE.txt
byte_search-0.5.9.dist-info/METADATA
byte_search-0.5.9.dist-info/WHEEL
byte_search-0.5.9.dist-info/top_level.txt
byte_search-0.5.9.dist-info/RECORD
